betterpython/__init__.py
betterpython/decorators.py
betterpython-0.1.0.dist-info/LICENSE.txt
betterpython-0.1.0.dist-info/METADATA
betterpython-0.1.0.dist-info/WHEEL
betterpython-0.1.0.dist-info/top_level.txt
betterpython-0.1.0.dist-info/RECORD
